Battleships_api/Ai.py
Battleships_api/Battleships.py
Battleships_api/CLIBattleships.py
Battleships_api/GameBoard.py
Battleships_api/Player.py
Battleships_api/References.py
Battleships_api/__init__.py
Battleships_api-0.1.2.dist-info/LICENSE
Battleships_api-0.1.2.dist-info/METADATA
Battleships_api-0.1.2.dist-info/WHEEL
Battleships_api-0.1.2.dist-info/top_level.txt
Battleships_api-0.1.2.dist-info/RECORD
