Metadata-Version: 2.1
Name: Battleships-api
Version: 0.1.2
Summary: Play Battleships, includes a basic cli front end
Home-page: https://github.com/simalpas/Battleships_project
Author: Simon Malpas
Author-email: 55702741+simalpas@users.noreply.github.com
License: UNKNOWN
Project-URL: Bug Tracker, https://github.com/simalpas/Battleships_project/issues
Platform: UNKNOWN
Classifier: Programming Language :: Python :: 3
Classifier: License :: OSI Approved :: MIT License
Classifier: Operating System :: OS Independent
Requires-Python: >=3.6
License-File: LICENSE
